VERILOG/RReyesL.v
// Lance Andrei T. Reyes S20

`timescale 1ns / 1ps

module boolean_function(F, A, B, C, D);
    input A, B, C, D;
    output F;

    // Intermediate signals for the maxterms
    wire m0, m1, m5, m8, m9, m13;

    // Maxterm 0: (A + B + C + D)
    // OR gate for maxterm 0
    or (m0, A, B, C, D);  

    // Maxterm 1: (A + B + ~C + D)
    // OR gate for maxterm 1
    or (m1, A, B, C, ~D);  

    // Maxterm 5: (~A + B + C + D)
    // OR gate for maxterm 5
    or (m5, A, ~B, C, ~D);  

    // Maxterm 8: (~A + B + ~C + ~D)
    // OR gate for maxterm 8
    or (m8, ~A, B, C, D); 

    // Maxterm 9: (A + B + ~C + D)
    // OR gate for maxterm 9
    or (m9, ~A, B, C, ~D);  

    // Maxterm 13: (A + ~B + C + ~D)
    // OR gate for maxterm 13
    or (m13, ~A, ~B, C, ~D); 

    // Final AND gate to combine all maxterms
    // AND gate for the final output
    and (F, m0, m1, m5, m8, m9, m13);  

endmodule

VERILOG/RReyesL_tb.v
// Lance Andrei T. Reyes S20

`timescale 1ns / 1ps

module boolean_function_tb;

    // Declare inputs
    reg A, B, C, D;
    
    // Declare output
    wire F;
    
    boolean_function dut (F, A, B, C, D);

    initial begin
        $display("Lance Andrei T. Reyes");
        $display("Boolean Function: F(A, B, C, D) = πM(0, 1, 5, 8, 9, 13)");
        $display("Verilog Model Type: Gate-level");
        $display("A B C D | F");
    end

   initial begin
        // Apply combinations 0000 to 1111 sequentially
        for (integer i = 0; i < 16; i = i + 1) begin
            {A, B, C, D} = i;
            #10;
        end
        
        // Return to 0000 after completing the loop, sequentially
        // Set inputs back to 0000
        {A, B, C, D} = 4'b0000;  
        #10;  // Wait for 10ns
    end

    // Dump waveform for viewing in GTKWave
    initial begin
        // File to store the waveform data
        $dumpfile("RReyesL.vcd");  
        // Dump all variables from this module
        $dumpvars(0, boolean_function_tb);  
    end

    // Monitor inputs and output
    initial begin
        $monitor("%b %b %b %b | %b", A, B, C, D, F);
    end

endmodule

VERILOG/RReyesL.vcd
$date
	Tue Feb 18 17:06:30 2025
$end
$version
	Icarus Verilog
$end
$timescale
	1ps
$end
$scope module boolean_function_tb $end
$var wire 1 ! F $end
$var reg 1 " A $end
$var reg 1 # B $end
$var reg 1 $ C $end
$var reg 1 % D $end
$scope module dut $end
$var wire 1 " A $end
$var wire 1 # B $end
$var wire 1 $ C $end
$var wire 1 % D $end
$var wire 1 ! F $end
$var wire 1 & m0 $end
$var wire 1 ' m1 $end
$var wire 1 ( m13 $end
$var wire 1 ) m5 $end
$var wire 1 * m8 $end
$var wire 1 + m9 $end
$upscope $end
$scope begin $ivl_for_loop0 $end
$var integer 32 , i [31:0] $end
$upscope $end
$upscope $end
$enddefinitions $end
$comment Show the parameter values. $end
$dumpall
$end
#0
$dumpvars
b0 ,
1+
1*
1)
1(
1'
0&
0%
0$
0#
0"
0!
$end
#10000
0'
1&
1%
b1 ,
#20000
1!
1'
1$
0%
b10 ,
#30000
1%
b11 ,
#40000
1#
0$
0%
b100 ,
#50000
0!
0)
1%
b101 ,
#60000
1!
1)
1$
0%
b110 ,
#70000
1%
b111 ,
#80000
0!
0*
1"
0#
0$
0%
b1000 ,
#90000
0+
1*
1%
b1001 ,
#100000
1!
1+
1$
0%
b1010 ,
#110000
1%
b1011 ,
#120000
1#
0$
0%
b1100 ,
#130000
0!
0(
1%
b1101 ,
#140000
1!
1(
1$
0%
b1110 ,
#150000
1%
b1111 ,
#160000
0!
0&
1*
0"
0#
0$
0%
b10000 ,
